<odoo>
    <data>
        <!-- Partner Tree View Extension -->
        <record id="view_res_partner_tree" model="ir.ui.view">
            <field name="name">res.partner.tree</field>
            <field name="model">res.partner</field>
            <field name="inherit_id" ref="base.view_partner_tree"/>
            <field name="arch" type="xml">
                <xpath expr="//tree" position="inside">
                    <field name="full_name" optional="show"/>
                    <field name="last_name" optional="show"/>
                    <field name="country_id" optional="show"/>
                    <field name="birth_date" optional="hide"/>
                    <field name="user_gender" optional="hide"/>
                    <field name="student_parent_id" optional="hide"/>
                    <field name="school_id" optional="hide"/>
                    <field name="teacher_id" optional="hide"/>
                    <field name="student_number" optional="hide"/>
                    <field name="educator_partner_id" optional="hide"/>
                    <field name="educator_subpartner_id" optional="hide"/>
                    <field name="student_id" optional="hide"/>
                    <field name="short_code" optional="hide"/>
                    <field name="educator_partner_code" optional="hide"/>
                    <field name="parent_email" optional="hide"/>
                    <field name="parent_phone" optional="hide"/>
                    <field name="partner_type" optional="show"/>
                    <field name="is_assign" optional="hide"/>
                    <field name="nationality" optional="hide"/>
                    <field name="age_category" optional="hide"/>
                    <field name="passport_number" optional="hide"/>
                    <field name="identity_vat_number" optional="hide"/>
                    <field name="special_pricelist_id" optional="hide"/>
                </xpath>
            </field>
        </record>
    </data>
</odoo>
